prime/__init__.py
prime/main.py
prime/projectmanager.py
prime/uix/__init__.py
prime/uix/button.py
prime/uix/filechooser.py
prime/uix/popup/__init__.py
prime/uix/popup/filepopup.py
stage/__init__.py
stage/main.py
stage/projectmanager.py
stage/uix/__init__.py
stage/uix/button.py
stage/uix/filechooser.py
stage/uix/popup/__init__.py
stage/uix/popup/filepopup.py
tsukushi/__init__.py
tsukushi/main.py
tsukushi/projectmanager.py
tsukushi/tsukushi.kv
tsukushi/fonts/NotoSansCJKjp/NotoSansCJKjp-Bold.otf
tsukushi/fonts/NotoSansCJKjp/NotoSansCJKjp-Regular.otf
tsukushi/images/action_bar.png
tsukushi/images/add-dir_icon.png
tsukushi/images/add-file_icon.png
tsukushi/images/button.png
tsukushi/images/button_pressed.png
tsukushi/images/code_input.png
tsukushi/images/explore_icon.png
tsukushi/images/generate-block-area.png
tsukushi/images/icon.png
tsukushi/images/logo.png
tsukushi/images/new-file_icon.png
tsukushi/images/open-file_icon.png
tsukushi/images/save-file_icon.png
tsukushi/uix/__init__.py
tsukushi/uix/button.py
tsukushi/uix/filechooser.py
tsukushi/uix/popup/__init__.py
tsukushi/uix/popup/filepopup.py
tsukushi-1.1.dist-info/LICENSE
tsukushi-1.1.dist-info/METADATA
tsukushi-1.1.dist-info/WHEEL
tsukushi-1.1.dist-info/entry_points.txt
tsukushi-1.1.dist-info/top_level.txt
tsukushi-1.1.dist-info/RECORD
