Metadata-Version: 2.1
Name: tsukushi
Version: 1.1
Summary: UNKNOWN
Home-page: https://github.com/Eleven-junichi2/tsukushi
Author: Junichi Suetsugu
License: UNKNOWN
Platform: UNKNOWN
Requires-Python: ==3.5.3
Requires-Dist: certifi (==2018.10.15)
Requires-Dist: chardet (==3.0.4)
Requires-Dist: docutils (==0.14)
Requires-Dist: idna (==2.7)
Requires-Dist: kivy (==1.10.1)
Requires-Dist: kivy-garden (==0.1.4)
Requires-Dist: pygments (==2.2.0)
Requires-Dist: requests (==2.20.1)
Requires-Dist: urllib3 (==1.23) ; python_version != "3.3.*"
